fastpluggy_plugin/debug_tools/__init__.py
fastpluggy_plugin/debug_tools/config.py
fastpluggy_plugin/debug_tools/plugin.py
fastpluggy_plugin/debug_tools/requirements_tools.py
fastpluggy_plugin/debug_tools/tasks.py
fastpluggy_plugin/debug_tools/router/__init__.py
fastpluggy_plugin/debug_tools/router/debug.py
fastpluggy_plugin/debug_tools/router/memory_tools.py
fastpluggy_plugin/debug_tools/router/menu_tools.py
fastpluggy_plugin/debug_tools/router/module_tools.py
fastpluggy_plugin/debug_tools/router/pool_info.py
fastpluggy_plugin/debug_tools/router/requirements.py
fastpluggy_plugin/debug_tools/router/settings.py
fastpluggy_plugin/debug_tools/router/task_thread_tools.py
fastpluggy_plugin/debug_tools/router/uvicorn.py
fastpluggy_plugin/debug_tools/router/websocket_tool.py
fastpluggy_plugin/debug_tools/static/debug.css
fastpluggy_plugin/debug_tools/templates/widgets/packages_view.html.j2
fastpluggy_plugin/debug_tools/templates/widgets/debug/debug_panel.html.j2
fastpluggy_plugin/debug_tools/widgets/__init__.py
fastpluggy_plugin/debug_tools/widgets/packages_view.py
fastpluggy_plugin/debug_tools/widgets/debug/__init__.py
fastpluggy_plugin/debug_tools/widgets/debug/debug_panel.py
fastpluggy_debug_tools-0.0.28.dist-info/METADATA
fastpluggy_debug_tools-0.0.28.dist-info/WHEEL
fastpluggy_debug_tools-0.0.28.dist-info/entry_points.txt
fastpluggy_debug_tools-0.0.28.dist-info/top_level.txt
fastpluggy_debug_tools-0.0.28.dist-info/RECORD
