Metadata-Version: 2.4
Name: fastpluggy-debug-tools
Version: 0.0.28
Summary: Debug Tools plugin for Fastpluggy
Author: FastPluggy Team
Requires-Python: >=3.10
Requires-Dist: FastPluggy>=0.2.50
Requires-Dist: psutil
Requires-Dist: packaging
Provides-Extra: all
Requires-Dist: pympler; extra == "all"
